djangocms_timed/__init__.py
djangocms_timed/cms_plugins.py
djangocms_timed/models.py
djangocms_timed/locale/de/LC_MESSAGES/django.mo
djangocms_timed/locale/de/LC_MESSAGES/django.po
djangocms_timed/locale/en/LC_MESSAGES/django.mo
djangocms_timed/locale/en/LC_MESSAGES/django.po
djangocms_timed/migrations/0001_initial.py
djangocms_timed/migrations/__init__.py
djangocms_timed/templates/djangocms_timed/timed.html
djangocms_timed-1.0.0.dist-info/DESCRIPTION.rst
djangocms_timed-1.0.0.dist-info/METADATA
djangocms_timed-1.0.0.dist-info/metadata.json
djangocms_timed-1.0.0.dist-info/RECORD
djangocms_timed-1.0.0.dist-info/top_level.txt
djangocms_timed-1.0.0.dist-info/WHEEL
tests/__init__.py
tests/settings.py
tests/test_plugins.py
