Metadata-Version: 2.0
Name: djangocms-timed
Version: 1.0.0
Summary: Timed addon for django CMS
Home-page: https://github.com/divio/djangocms-timed
Author: Divio AG
Author-email: info@divio.ch
License: BSD License
Platform: OS Independent
Classifier: Development Status :: 4 - Beta
Classifier: Environment :: Web Environment
Classifier: Framework :: Django
Classifier: Intended Audience :: Developers
Classifier: License :: OSI Approved :: BSD License
Classifier: Operating System :: OS Independent
Classifier: Programming Language :: Python
Classifier: Topic :: Internet :: WWW/HTTP :: Dynamic Content
Classifier: Topic :: Software Development
Classifier: Topic :: Software Development :: Libraries :: Application Frameworks
